README.md
setup.py
debug_world/__init__.py
debug_world/print_str.py
debug_world_fkh.egg-info/PKG-INFO
debug_world_fkh.egg-info/SOURCES.txt
debug_world_fkh.egg-info/dependency_links.txt
debug_world_fkh.egg-info/top_level.txt
demo/__init__.py
demo/hello.py