Metadata-Version: 2.1
Name: debug-world-fkh
Version: 0.0.1
Summary: PyPI Tutorial
Home-page: https://github.com/
Author: fangkanghua
Author-email: fangkanghua@corp.netease.com
License: UNKNOWN
Platform: UNKNOWN
